{
  "collectionName": "components_policy_items",
  "info": {
    "displayName": "Items"
  },
  "options": {},
  "attributes": {
    "Title": {
      "type": "string"
    },
    "Content": {
      "type": "customField",
      "customField": "plugin::ckeditor5.CKEditor",
      "options": {
        "preset": "defaultHtml"
      }
    },
    "Image": {
      "type": "media",
      "multiple": false,
      "allowedTypes": [
        "images",
        "files",
        "videos",
        "audios"
      ]
    }
  },
  "config": {}
}
